MANIFEST.in
README.markdown
dev-requirements.txt
requirements.txt
setup.py
watson/__init__.py
watson/client.py
watson/client_test.py
watson/core.py
watson/core_test.py
watson/daemon.py
watson/test_helper.py
watson_ci.egg-info/PKG-INFO
watson_ci.egg-info/SOURCES.txt
watson_ci.egg-info/dependency_links.txt
watson_ci.egg-info/entry_points.txt
watson_ci.egg-info/not-zip-safe
watson_ci.egg-info/requires.txt
watson_ci.egg-info/top_level.txt